ML_medic_kit/__init__.py
ML_medic_kit/cross_validation.py
ML_medic_kit/data_preprocessing.py
ML_medic_kit/hyperparameter_tuning.py
ML_medic_kit/model_evaluation.py
ML_medic_kit/model_selection.py
ML_medic_kit/visualisation.py
ML_medic_kit/data/breast_cancer_data.csv
ML_medic_kit/data/heart_disease_data.csv
ML_medic_kit-0.2.1.dist-info/LICENSE
ML_medic_kit-0.2.1.dist-info/METADATA
ML_medic_kit-0.2.1.dist-info/WHEEL
ML_medic_kit-0.2.1.dist-info/top_level.txt
ML_medic_kit-0.2.1.dist-info/RECORD
