Metadata-Version: 2.1
Name: ML-medic-kit
Version: 0.2.1
Summary: The Machine Learning Medic Kit is designed to enhance the capabilities of health data scientists tackling binary classification problems
Home-page: https://github.com/marthadinsdale/hds_ca2
Author: Martha Dinsdale, Holly Manning
Author-email: md661@exeter.ac.uk
License: The MIT License (MIT)
Classifier: Programming Language :: Python :: 3.6
Classifier: Programming Language :: Python :: 3.7
Classifier: Programming Language :: Python :: 3.8
Classifier: License :: OSI Approved :: MIT License
Classifier: Operating System :: OS Independent
Requires-Python: >=3.6.9
License-File: LICENSE
Requires-Dist: jupyterlab ==1.2.6
Requires-Dist: matplotlib ==3.1.3
Requires-Dist: numpy ==1.18.1
Requires-Dist: pandas ==1.0.1
Requires-Dist: pytest ==5.3.5
Requires-Dist: scipy ==1.4.1
Requires-Dist: seaborn ==0.10.0
Requires-Dist: scikit-learn ==0.24.1
Requires-Dist: pytest-cov ==2.10.0
Requires-Dist: setuptools >=51.1.2
Requires-Dist: twine >=3.3.0
Requires-Dist: wheel >0.36.2
Requires-Dist: shap ==0.40.0
